qubit_approximant/__init__.py
qubit_approximant/_version.py
qubit_approximant/benchmarking/__init__.py
qubit_approximant/benchmarking/functions/__init__.py
qubit_approximant/benchmarking/functions/functions.py
qubit_approximant/benchmarking/metrics/__init__.py
qubit_approximant/benchmarking/metrics/metric_results.py
qubit_approximant/benchmarking/metrics/metrics.py
qubit_approximant/benchmarking/plot/__init__.py
qubit_approximant/benchmarking/plot/plot.py
qubit_approximant/benchmarking/seeds/__init__.py
qubit_approximant/benchmarking/seeds/seeds.py
qubit_approximant/core/__init__.py
qubit_approximant/core/circuit/__init__.py
qubit_approximant/core/circuit/_gates_and_grads.py
qubit_approximant/core/circuit/circuit.py
qubit_approximant/core/cost/__init__.py
qubit_approximant/core/cost/_cost_metrics.py
qubit_approximant/core/cost/cost.py
qubit_approximant/core/optimizer/__init__.py
qubit_approximant/core/optimizer/multilayer_optimizer.py
qubit_approximant/core/optimizer/optimizer.py
qubit_approximant-1.0.0.dist-info/LICENSE
qubit_approximant-1.0.0.dist-info/METADATA
qubit_approximant-1.0.0.dist-info/WHEEL
qubit_approximant-1.0.0.dist-info/top_level.txt
qubit_approximant-1.0.0.dist-info/RECORD
