Metadata-Version: 2.1
Name: qubit-approximant
Version: 1.0.0
Summary: Approximate a function using a single qubit.
Author: Pablo V. Parellada
License: GNU GENERAL PUBLIC LICENSE
Project-URL: repository, https://github.com/pablovegan/QubitApproximant
Project-URL: documentation, https://pablovegan.github.io/QubitApproximant/
Platform: unix
Platform: linux
Platform: osx
Platform: cygwin
Platform: win32
Classifier: Programming Language :: Python :: 3
Requires-Python: >=3.8
License-File: LICENSE
Requires-Dist: numpy
Requires-Dist: scipy
Requires-Dist: pandas
Requires-Dist: dill
Requires-Dist: pathos
Requires-Dist: pennylane
Requires-Dist: mpi4py
Provides-Extra: dev
Requires-Dist: pytest ; extra == 'dev'
Requires-Dist: codecov ; extra == 'dev'
Requires-Dist: pytest-cov ; extra == 'dev'
Requires-Dist: pre-commit ; extra == 'dev'
Requires-Dist: black ; extra == 'dev'
Requires-Dist: twine ; extra == 'dev'
Requires-Dist: check-manifest ; extra == 'dev'
Requires-Dist: mkdocs ; extra == 'dev'
Requires-Dist: mkdocstrings ; extra == 'dev'
Requires-Dist: mkdocstrings[python] ; extra == 'dev'
Requires-Dist: mkdocs-material ; extra == 'dev'
Requires-Dist: Pygments ; extra == 'dev'
Requires-Dist: python-markdown-math ; extra == 'dev'
Requires-Dist: mkdocs-gen-files ; extra == 'dev'
Requires-Dist: mkdocs-literate-nav ; extra == 'dev'
Requires-Dist: mkdocs-section-index ; extra == 'dev'
Requires-Dist: mkdocs-same-dir ; extra == 'dev'
Requires-Dist: mkdocs-autorefs ; extra == 'dev'
